beetsplug/bandcamp/__init__.py
beetsplug/bandcamp/album_name.py
beetsplug/bandcamp/catalognum.py
beetsplug/bandcamp/genres_lookup.py
beetsplug/bandcamp/helpers.py
beetsplug/bandcamp/http.py
beetsplug/bandcamp/metaguru.py
beetsplug/bandcamp/names.py
beetsplug/bandcamp/search.py
beetsplug/bandcamp/track.py
beetsplug/bandcamp/tracks.py
beetcamp-0.23.0.dist-info/LICENSE
beetcamp-0.23.0.dist-info/METADATA
beetcamp-0.23.0.dist-info/WHEEL
beetcamp-0.23.0.dist-info/entry_points.txt
beetcamp-0.23.0.dist-info/RECORD
