Metadata-Version: 2.3
Name: beetcamp
Version: 0.23.0
Summary: Bandcamp autotagger source for beets (http://beets.io).
License: GPL-2.0
Keywords: music,bandcamp,beets,metadata
Author: Šarūnas Nejus
Author-email: snejus@pm.me
Requires-Python: >=3.9, <4
Classifier: Environment :: Console
Classifier: Intended Audience :: End Users/Desktop
Classifier: Operating System :: OS Independent
Classifier: Topic :: Multimedia :: Sound/Audio
Classifier: Topic :: Text Processing :: General
Requires-Dist: beets[fetchart] (>=1.5)
Requires-Dist: httpx (>=0.27.0)
Requires-Dist: packaging (>=24.0)
Requires-Dist: pycountry (>=20.7.3)
Project-URL: Bug Tracker, https://github.com/snejus/beetcamp/issues
Project-URL: Homepage, https://github.com/snejus/beetcamp
Project-URL: Repository, https://github.com/snejus/beetcamp
Project-URL: changelog, https://github.com/snejus/beetcamp/blob/master/CHANGELOG.md
